setup.py
devdoo/__init__.py
devdoo/console.py
devdoo/database.py
devdoo/datafilter.py
devdoo/datarest.py
devdoo/datarest_db.py
devdoo/datatypes.py
devdoo/decode_types.py
devdoo/devdoo_brokers.py
devdoo/devdoo_database.py
devdoo/devdoo_services.py
devdoo/service.py
devdoo/service_db.py
devdoo/status.py
devdoo/validate.py
devdoo/yaml/__init__.py
devdoo/yaml/composer.py
devdoo/yaml/constructor.py
devdoo/yaml/cyaml.py
devdoo/yaml/dumper.py
devdoo/yaml/emitter.py
devdoo/yaml/error.py
devdoo/yaml/events.py
devdoo/yaml/loader.py
devdoo/yaml/nodes.py
devdoo/yaml/parser.py
devdoo/yaml/reader.py
devdoo/yaml/representer.py
devdoo/yaml/resolver.py
devdoo/yaml/scanner.py
devdoo/yaml/serializer.py
devdoo/yaml/tokens.py
devdoo/yaml/__init__.py
devdoo/yaml/composer.py
devdoo/yaml/constructor.py
devdoo/yaml/cyaml.py
devdoo/yaml/dumper.py
devdoo/yaml/emitter.py
devdoo/yaml/error.py
devdoo/yaml/events.py
devdoo/yaml/loader.py
devdoo/yaml/nodes.py
devdoo/yaml/parser.py
devdoo/yaml/reader.py
devdoo/yaml/representer.py
devdoo/yaml/resolver.py
devdoo/yaml/scanner.py
devdoo/yaml/serializer.py
devdoo/yaml/tokens.py
packagetest85.egg-info/PKG-INFO
packagetest85.egg-info/SOURCES.txt
packagetest85.egg-info/dependency_links.txt
packagetest85.egg-info/not-zip-safe
packagetest85.egg-info/top_level.txt