Metadata-Version: 1.0
Name: packagetest85
Version: 0.85
Summary: Test2
Home-page: http://github.com/storborg/funniest
Author: PulStar
Author-email: pulstar@gmail.com
License: MIT
Platform: UNKNOWN
